pyepr/__init__.py
pyepr/_version.py
pyepr/classes.py
pyepr/colors.py
pyepr/config.py
pyepr/criteria.py
pyepr/dataset.py
pyepr/fieldsweep_analysis.py
pyepr/hardware/.DS_Store
pyepr/hardware/Bruker_AWG.py
pyepr/hardware/Bruker_MPFU.py
pyepr/hardware/Bruker_tools.py
pyepr/hardware/ETH_awg.py
pyepr/hardware/ETH_awg_load.py
pyepr/hardware/PyEPR_control.py
pyepr/hardware/XeprAPI_link.py
pyepr/hardware/__init__.py
pyepr/hardware/dummy.py
pyepr/hardware/dummy_xepr.py
pyepr/hardware/xepr_experiments.py
pyepr/pulses.py
pyepr/relaxation_analysis.py
pyepr/resonator_profile_analysis.py
pyepr/sequences.py
pyepr/tools.py
pyepr/utils.py
pyepr_esr-1.0.dist-info/LICENSE
pyepr_esr-1.0.dist-info/METADATA
pyepr_esr-1.0.dist-info/WHEEL
pyepr_esr-1.0.dist-info/RECORD
