Metadata-Version: 2.3
Name: pyEPR-ESR
Version: 1.0
Summary: 
Author: Hugo Karas
Author-email: hkaras@ethz.ch
Requires-Python: >=3.11,<3.13
Classifier: Programming Language :: Python :: 3
Classifier: Programming Language :: Python :: 3.11
Classifier: Programming Language :: Python :: 3.12
Requires-Dist: deerlab (>=1.1.4,<2.0.0)
Requires-Dist: h5netcdf (>=1.4.0,<2.0.0)
Requires-Dist: matplotlib (>=3.9.2,<4.0.0)
Requires-Dist: numba (>0.60.0)
Requires-Dist: numpy (>2.1)
Requires-Dist: pyyaml (>=6.0.2,<7.0.0)
Requires-Dist: scipy (>=1.14.1,<2.0.0)
Requires-Dist: toml (>=0.10.2,<0.11.0)
Requires-Dist: xarray (>=2025,<2026)
